{
  "id": "52f04985-cdca-4dd1-a2c3-afc34239e7a1",
  "task_type": "email",
  "zone": "email",
  "content": "[Claimed from Needs_Action] From: unknown | Subject: sim_20260305T083833Z_0e441790\n{\n  \"id\": \"0e441790-4168-4df7-aece-5af621f1a8bd\",\n  \"task_type\": \"send_email\",\n  \"zone\": \"email\",\n  \"content\": \"Draft a follow-up email to client Acme Corp re: pending proposal\",\n  \"source\": \"company_simulation\",\n  \"created_at\": \"2026-03-05T08:38:33.929436+00:00\",\n  \"status\": \"pending\"\n}",
  "created_at": "2026-03-05T08:39:01.458539Z",
  "status": "pending"
}